rtr_componentes/__init__.py
st_hierarchicalGrid/__init__.py
st_hierarchicalGrid/frontend/dist/bootstrap.min.css
st_hierarchicalGrid/frontend/dist/index.html
st_hierarchicalGrid/frontend/dist/vite.svg
st_hierarchicalGrid/frontend/dist/assets/html2canvas.esm-CBrSDip1.js
st_hierarchicalGrid/frontend/dist/assets/index-Da2WPbqB.js
st_hierarchicalGrid/frontend/dist/assets/index-DzftQ9XA.css
st_hierarchicalGrid/frontend/dist/assets/index.es-CoP1iHAK.js
st_hierarchicalGrid/frontend/dist/assets/purify.es-CQJ0hv7W.js
st_hierarchicalGrid/frontend/node_modules/flatted/python/flatted.py
st_orgChart/__init__.py
st_orgChart/frontend/dist/index.html
st_orgChart/frontend/dist/vite.svg
st_orgChart/frontend/dist/assets/html2canvas.esm-CBrSDip1.js
st_orgChart/frontend/dist/assets/index-CWPKtmeO.js
st_orgChart/frontend/dist/assets/index-_RR1tAEj.css
st_orgChart/frontend/dist/assets/index.es-6NTqqajs.js
st_orgChart/frontend/dist/assets/purify.es-CQJ0hv7W.js
st_orgChart/frontend/node_modules/flatted/python/flatted.py
streamlit_rtr_components-1.0.7.dist-info/licenses/LICENSE
streamlit_rtr_components-1.0.7.dist-info/METADATA
streamlit_rtr_components-1.0.7.dist-info/WHEEL
streamlit_rtr_components-1.0.7.dist-info/top_level.txt
streamlit_rtr_components-1.0.7.dist-info/RECORD
