Metadata-Version: 2.4
Name: streamlit-rtr-components
Version: 1.0.7
Summary: Streamlit components: Org Chart e Hierarchical Grid
Author-email: "Artur R. Oliveira" <arturroliveira87@gmail.com>
Requires-Python: >=3.8
License-File: LICENSE
Requires-Dist: streamlit>=1.24
Provides-Extra: devel
Requires-Dist: wheel; extra == "devel"
Requires-Dist: pytest==7.4.0; extra == "devel"
Requires-Dist: playwright==1.48.0; extra == "devel"
Requires-Dist: requests==2.31.0; extra == "devel"
Requires-Dist: pytest-playwright-snapshot==1.0; extra == "devel"
Requires-Dist: pytest-rerunfailures==12.0; extra == "devel"
Dynamic: license-file
